sphinxcontrib/rigado/__init__.py
sphinxcontrib/rigado/inventory-builder.py
sphinxcontrib/rigado/tablelist.py
sphinxcontrib_rigado-0.0.1.dist-info/METADATA
sphinxcontrib_rigado-0.0.1.dist-info/RECORD
sphinxcontrib_rigado-0.0.1.dist-info/WHEEL
sphinxcontrib_rigado-0.0.1.dist-info/top_level.txt
