Metadata-Version: 2.1
Name: sphinxcontrib-rigado
Version: 0.0.1
Summary: Sphinx extensions for Rigado
Home-page: https://git.rigado.com/documentation/sphinx
Author: Spencer Williams
Author-email: spencer.williams@rigado.com
License: MIT
Platform: UNKNOWN
